{
	"format_version": "1.12.0",
	"minecraft:geometry": [
		{
			"description": {
				"identifier": "geometry.unknown",
				"texture_width": 16,
				"texture_height": 16,
				"visible_bounds_width": 2,
				"visible_bounds_height": 1.5,
				"visible_bounds_offset": [0, 0.25, 0]
			},
			"bones": [
				{
					"name": "gun",
					"pivot": [0, 0, 0]
				},
				{
					"name": "cover_L",
					"parent": "gun",
					"pivot": [0.55, 4.6607, -4.02291],
					"cubes": [
						{
							"origin": [0.6, 3.6, -7.5],
							"size": [0.1, 1.16066, 3.9],
							"uv": {
								"north": {"uv": [15, 15], "uv_size": [1, 1]},
								"east": {"uv": [15, 15], "uv_size": [1, 1]},
								"south": {"uv": [15, 15], "uv_size": [1, 1]},
								"west": {"uv": [15, 15], "uv_size": [1, 1]},
								"up": {"uv": [16, 16], "uv_size": [-1, -1]},
								"down": {"uv": [16, 16], "uv_size": [-1, -1]}
							}
						},
						{
							"origin": [0.5, 4.96066, -7.5],
							"size": [0.1, 0.70711, 4.32426],
							"uv": {
								"north": {"uv": [15, 15], "uv_size": [1, 1]},
								"east": {"uv": [15, 15], "uv_size": [1, 1]},
								"south": {"uv": [15, 15], "uv_size": [1, 1]},
								"west": {"uv": [15, 15], "uv_size": [1, 1]},
								"up": {"uv": [16, 16], "uv_size": [-1, -1]},
								"down": {"uv": [16, 16], "uv_size": [-1, -1]}
							}
						},
						{
							"origin": [0.5, 4.73137, -7.5],
							"size": [0.2, 0.22929, 5.03137],
							"uv": {
								"north": {"uv": [15, 15], "uv_size": [1, 1]},
								"east": {"uv": [15, 15], "uv_size": [1, 1]},
								"south": {"uv": [15, 15], "uv_size": [1, 1]},
								"west": {"uv": [15, 15], "uv_size": [1, 1]},
								"up": {"uv": [16, 16], "uv_size": [-1, -1]},
								"down": {"uv": [16, 16], "uv_size": [-1, -1]}
							}
						},
						{
							"origin": [0.6, 3.9364, -3.98787],
							"size": [0.1, 0.2, 1.6],
							"pivot": [0.65, 4.2364, -3.38787],
							"rotation": [45, 0, 0],
							"uv": {
								"north": {"uv": [15, 15], "uv_size": [1, 1]},
								"east": {"uv": [15, 15], "uv_size": [1, 1]},
								"south": {"uv": [15, 15], "uv_size": [1, 1]},
								"west": {"uv": [15, 15], "uv_size": [1, 1]},
								"up": {"uv": [16, 16], "uv_size": [-1, -1]},
								"down": {"uv": [16, 16], "uv_size": [-1, -1]}
							}
						},
						{
							"origin": [0.6, 4.0364, -3.78787],
							"size": [0.1, 0.4, 1.2],
							"pivot": [0.65, 4.2364, -3.38787],
							"rotation": [45, 0, 0],
							"uv": {
								"north": {"uv": [15, 15], "uv_size": [1, 1]},
								"east": {"uv": [15, 15], "uv_size": [1, 1]},
								"south": {"uv": [15, 15], "uv_size": [1, 1]},
								"west": {"uv": [15, 15], "uv_size": [1, 1]},
								"up": {"uv": [16, 16], "uv_size": [-1, -1]},
								"down": {"uv": [16, 16], "uv_size": [-1, -1]}
							}
						},
						{
							"origin": [0.6, 4.3364, -3.48787],
							"size": [0.1, 0.4, 0.6],
							"pivot": [0.65, 4.2364, -3.38787],
							"rotation": [45, 0, 0],
							"uv": {
								"north": {"uv": [15, 15], "uv_size": [1, 1]},
								"east": {"uv": [15, 15], "uv_size": [1, 1]},
								"south": {"uv": [15, 15], "uv_size": [1, 1]},
								"west": {"uv": [15, 15], "uv_size": [1, 1]},
								"up": {"uv": [16, 16], "uv_size": [-1, -1]},
								"down": {"uv": [16, 16], "uv_size": [-1, -1]}
							}
						},
						{
							"origin": [0.5, 4.74142, -1.99792],
							"size": [0.1, 1, 0.2],
							"pivot": [0.65, 4.04142, -2.39792],
							"rotation": [45, 0, 0],
							"uv": {
								"north": {"uv": [15, 15], "uv_size": [1, 1]},
								"east": {"uv": [15, 15], "uv_size": [1, 1]},
								"south": {"uv": [15, 15], "uv_size": [1, 1]},
								"west": {"uv": [15, 15], "uv_size": [1, 1]},
								"up": {"uv": [16, 16], "uv_size": [-1, -1]},
								"down": {"uv": [16, 16], "uv_size": [-1, -1]}
							}
						},
						{
							"origin": [0.5, 4.94142, -2.19792],
							"size": [0.1, 0.6, 0.3],
							"pivot": [0.65, 4.04142, -2.39792],
							"rotation": [45, 0, 0],
							"uv": {
								"north": {"uv": [15, 15], "uv_size": [1, 1]},
								"east": {"uv": [15, 15], "uv_size": [1, 1]},
								"south": {"uv": [15, 15], "uv_size": [1, 1]},
								"west": {"uv": [15, 15], "uv_size": [1, 1]},
								"up": {"uv": [16, 16], "uv_size": [-1, -1]},
								"down": {"uv": [16, 16], "uv_size": [-1, -1]}
							}
						},
						{
							"origin": [0.5, 5.14142, -2.29792],
							"size": [0.1, 0.2, 0.2],
							"pivot": [0.65, 4.04142, -2.39792],
							"rotation": [45, 0, 0],
							"uv": {
								"north": {"uv": [15, 15], "uv_size": [1, 1]},
								"east": {"uv": [15, 15], "uv_size": [1, 1]},
								"south": {"uv": [15, 15], "uv_size": [1, 1]},
								"west": {"uv": [15, 15], "uv_size": [1, 1]},
								"up": {"uv": [16, 16], "uv_size": [-1, -1]},
								"down": {"uv": [16, 16], "uv_size": [-1, -1]}
							}
						},
						{
							"origin": [-0.5, 3.6, -7.5],
							"size": [1.2, 0.1, 3.9],
							"uv": {
								"north": {"uv": [15, 15], "uv_size": [1, 1]},
								"east": {"uv": [15, 15], "uv_size": [1, 1]},
								"south": {"uv": [15, 15], "uv_size": [1, 1]},
								"west": {"uv": [15, 15], "uv_size": [1, 1]},
								"up": {"uv": [16, 16], "uv_size": [-1, -1]},
								"down": {"uv": [16, 16], "uv_size": [-1, -1]}
							}
						}
					]
				},
				{
					"name": "hole",
					"parent": "cover_L",
					"pivot": [0, 0, -0.2],
					"cubes": [
						{
							"origin": [0.381, 3.28, -5.88],
							"size": [0, 0.65, 2.08],
							"pivot": [0.376, 3.6, -4.84],
							"rotation": [0, 0, 90],
							"uv": {
								"west": {"uv": [0, 10], "uv_size": [16, 5]}
							}
						},
						{
							"origin": [0.705, 3.595, -5.88],
							"size": [0, 1.3, 2.08],
							"uv": {
								"west": {"uv": [0, 0], "uv_size": [16, 10]}
							}
						}
					]
				},
				{
					"name": "cover_R",
					"parent": "gun",
					"pivot": [-0.55, 4.85748, -4.0017],
					"cubes": [
						{
							"origin": [-0.7, 3.6, -7.5],
							"size": [0.1, 1.16066, 3.9],
							"uv": {
								"north": {"uv": [15, 15], "uv_size": [1, 1]},
								"east": {"uv": [15, 15], "uv_size": [1, 1]},
								"south": {"uv": [15, 15], "uv_size": [1, 1]},
								"west": {"uv": [15, 15], "uv_size": [1, 1]},
								"up": {"uv": [16, 16], "uv_size": [-1, -1]},
								"down": {"uv": [16, 16], "uv_size": [-1, -1]}
							}
						},
						{
							"origin": [-0.6, 4.96066, -7.5],
							"size": [0.1, 0.70711, 4.32426],
							"uv": {
								"north": {"uv": [15, 15], "uv_size": [1, 1]},
								"east": {"uv": [15, 15], "uv_size": [1, 1]},
								"south": {"uv": [15, 15], "uv_size": [1, 1]},
								"west": {"uv": [15, 15], "uv_size": [1, 1]},
								"up": {"uv": [16, 16], "uv_size": [-1, -1]},
								"down": {"uv": [16, 16], "uv_size": [-1, -1]}
							}
						},
						{
							"origin": [-0.7, 4.73137, -7.5],
							"size": [0.2, 0.22929, 5.03137],
							"uv": {
								"north": {"uv": [15, 15], "uv_size": [1, 1]},
								"east": {"uv": [15, 15], "uv_size": [1, 1]},
								"south": {"uv": [15, 15], "uv_size": [1, 1]},
								"west": {"uv": [15, 15], "uv_size": [1, 1]},
								"up": {"uv": [16, 16], "uv_size": [-1, -1]},
								"down": {"uv": [16, 16], "uv_size": [-1, -1]}
							}
						},
						{
							"origin": [-0.7, 3.9364, -3.98787],
							"size": [0.1, 0.2, 1.6],
							"pivot": [-0.65, 4.2364, -3.38787],
							"rotation": [45, 0, 0],
							"uv": {
								"north": {"uv": [15, 15], "uv_size": [1, 1]},
								"east": {"uv": [15, 15], "uv_size": [1, 1]},
								"south": {"uv": [15, 15], "uv_size": [1, 1]},
								"west": {"uv": [15, 15], "uv_size": [1, 1]},
								"up": {"uv": [16, 16], "uv_size": [-1, -1]},
								"down": {"uv": [16, 16], "uv_size": [-1, -1]}
							}
						},
						{
							"origin": [-0.7, 4.0364, -3.78787],
							"size": [0.1, 0.4, 1.2],
							"pivot": [-0.65, 4.2364, -3.38787],
							"rotation": [45, 0, 0],
							"uv": {
								"north": {"uv": [15, 15], "uv_size": [1, 1]},
								"east": {"uv": [15, 15], "uv_size": [1, 1]},
								"south": {"uv": [15, 15], "uv_size": [1, 1]},
								"west": {"uv": [15, 15], "uv_size": [1, 1]},
								"up": {"uv": [16, 16], "uv_size": [-1, -1]},
								"down": {"uv": [16, 16], "uv_size": [-1, -1]}
							}
						},
						{
							"origin": [-0.7, 4.3364, -3.48787],
							"size": [0.1, 0.4, 0.6],
							"pivot": [-0.65, 4.2364, -3.38787],
							"rotation": [45, 0, 0],
							"uv": {
								"north": {"uv": [15, 15], "uv_size": [1, 1]},
								"east": {"uv": [15, 15], "uv_size": [1, 1]},
								"south": {"uv": [15, 15], "uv_size": [1, 1]},
								"west": {"uv": [15, 15], "uv_size": [1, 1]},
								"up": {"uv": [16, 16], "uv_size": [-1, -1]},
								"down": {"uv": [16, 16], "uv_size": [-1, -1]}
							}
						},
						{
							"origin": [-0.6, 4.74142, -1.99792],
							"size": [0.1, 1, 0.2],
							"pivot": [-0.65, 4.04142, -2.39792],
							"rotation": [45, 0, 0],
							"uv": {
								"north": {"uv": [15, 15], "uv_size": [1, 1]},
								"east": {"uv": [15, 15], "uv_size": [1, 1]},
								"south": {"uv": [15, 15], "uv_size": [1, 1]},
								"west": {"uv": [15, 15], "uv_size": [1, 1]},
								"up": {"uv": [16, 16], "uv_size": [-1, -1]},
								"down": {"uv": [16, 16], "uv_size": [-1, -1]}
							}
						},
						{
							"origin": [-0.6, 4.94142, -2.19792],
							"size": [0.1, 0.6, 0.3],
							"pivot": [-0.65, 4.04142, -2.39792],
							"rotation": [45, 0, 0],
							"uv": {
								"north": {"uv": [15, 15], "uv_size": [1, 1]},
								"east": {"uv": [15, 15], "uv_size": [1, 1]},
								"south": {"uv": [15, 15], "uv_size": [1, 1]},
								"west": {"uv": [15, 15], "uv_size": [1, 1]},
								"up": {"uv": [16, 16], "uv_size": [-1, -1]},
								"down": {"uv": [16, 16], "uv_size": [-1, -1]}
							}
						},
						{
							"origin": [-0.6, 5.14142, -2.29792],
							"size": [0.1, 0.2, 0.2],
							"pivot": [-0.65, 4.04142, -2.39792],
							"rotation": [45, 0, 0],
							"uv": {
								"north": {"uv": [15, 15], "uv_size": [1, 1]},
								"east": {"uv": [15, 15], "uv_size": [1, 1]},
								"south": {"uv": [15, 15], "uv_size": [1, 1]},
								"west": {"uv": [15, 15], "uv_size": [1, 1]},
								"up": {"uv": [16, 16], "uv_size": [-1, -1]},
								"down": {"uv": [16, 16], "uv_size": [-1, -1]}
							}
						},
						{
							"origin": [-0.6, 5.56777, -7.5],
							"size": [1, 0.1, 4.32426],
							"uv": {
								"north": {"uv": [15, 15], "uv_size": [1, 1]},
								"east": {"uv": [15, 15], "uv_size": [1, 1]},
								"south": {"uv": [15, 15], "uv_size": [1, 1]},
								"west": {"uv": [15, 15], "uv_size": [1, 1]},
								"up": {"uv": [16, 16], "uv_size": [-1, -1]},
								"down": {"uv": [16, 16], "uv_size": [-1, -1]}
							}
						}
					]
				},
				{
					"name": "trigger",
					"parent": "gun",
					"pivot": [0, 3.82371, -2.26603],
					"cubes": [
						{
							"origin": [-0.3, 3.40814, -2.11345],
							"size": [0.6, 0.5, 0.1],
							"pivot": [0, 3.55814, -2.06345],
							"rotation": [25, 0, 0],
							"uv": {
								"north": {"uv": [15, 15], "uv_size": [1, 1]},
								"east": {"uv": [15, 15], "uv_size": [1, 1]},
								"south": {"uv": [15, 15], "uv_size": [1, 1]},
								"west": {"uv": [15, 15], "uv_size": [1, 1]},
								"up": {"uv": [16, 16], "uv_size": [-1, -1]},
								"down": {"uv": [16, 16], "uv_size": [-1, -1]}
							}
						},
						{
							"origin": [-0.3, 2.94293, -1.94561],
							"size": [0.6, 0.5, 0.1],
							"pivot": [0, 4.69293, -1.89561],
							"rotation": [-5, 0, 0],
							"uv": {
								"north": {"uv": [15, 15], "uv_size": [1, 1]},
								"east": {"uv": [15, 15], "uv_size": [1, 1]},
								"south": {"uv": [15, 15], "uv_size": [1, 1]},
								"west": {"uv": [15, 15], "uv_size": [1, 1]},
								"up": {"uv": [16, 16], "uv_size": [-1, -1]},
								"down": {"uv": [16, 16], "uv_size": [-1, -1]}
							}
						}
					]
				},
				{
					"name": "body",
					"parent": "gun",
					"pivot": [0, 3.05377, -1.36496],
					"cubes": [
						{
							"origin": [-0.5, 0.26043, -1.17848],
							"size": [1, 2.5, 1.5],
							"pivot": [0, 1.51043, -0.42848],
							"rotation": [25, 0, 0],
							"uv": {
								"north": {"uv": [15, 15], "uv_size": [1, 1]},
								"east": {"uv": [15, 15], "uv_size": [1, 1]},
								"south": {"uv": [15, 15], "uv_size": [1, 1]},
								"west": {"uv": [15, 15], "uv_size": [1, 1]},
								"up": {"uv": [16, 16], "uv_size": [-1, -1]},
								"down": {"uv": [16, 16], "uv_size": [-1, -1]}
							}
						},
						{
							"origin": [-0.5, 2.32635, -1.63649],
							"size": [1, 2.5, 1.5],
							"uv": {
								"north": {"uv": [15, 15], "uv_size": [1, 1]},
								"east": {"uv": [15, 15], "uv_size": [1, 1]},
								"south": {"uv": [15, 15], "uv_size": [1, 1]},
								"west": {"uv": [15, 15], "uv_size": [1, 1]},
								"up": {"uv": [16, 16], "uv_size": [-1, -1]},
								"down": {"uv": [16, 16], "uv_size": [-1, -1]}
							}
						},
						{
							"origin": [-0.3, 2.62635, -3.13648],
							"size": [0.6, 0.2, 1.5],
							"uv": {
								"north": {"uv": [15, 15], "uv_size": [1, 1]},
								"east": {"uv": [15, 15], "uv_size": [1, 1]},
								"south": {"uv": [15, 15], "uv_size": [1, 1]},
								"west": {"uv": [15, 15], "uv_size": [1, 1]},
								"up": {"uv": [16, 16], "uv_size": [-1, -1]},
								"down": {"uv": [16, 16], "uv_size": [-1, -1]}
							}
						},
						{
							"origin": [-0.3, 3.21715, -3.90642],
							"size": [0.6, 0.2, 1.3],
							"pivot": [0, 3.26715, -3.25642],
							"rotation": [-75, 0, 0],
							"uv": {
								"north": {"uv": [15, 15], "uv_size": [1, 1]},
								"east": {"uv": [15, 15], "uv_size": [1, 1]},
								"south": {"uv": [15, 15], "uv_size": [1, 1]},
								"west": {"uv": [15, 15], "uv_size": [1, 1]},
								"up": {"uv": [16, 16], "uv_size": [-1, -1]},
								"down": {"uv": [16, 16], "uv_size": [-1, -1]}
							}
						},
						{
							"origin": [-0.5, 3.83346, -7.34359],
							"size": [1, 1.7, 6.5],
							"uv": {
								"north": {"uv": [15, 15], "uv_size": [1, 1]},
								"east": {"uv": [15, 15], "uv_size": [1, 1]},
								"south": {"uv": [15, 15], "uv_size": [1, 1]},
								"west": {"uv": [15, 15], "uv_size": [1, 1]},
								"up": {"uv": [16, 16], "uv_size": [-1, -1]},
								"down": {"uv": [16, 16], "uv_size": [-1, -1]}
							}
						},
						{
							"origin": [-0.5, 3.92991, -1.3007],
							"size": [1, 1, 0.5],
							"pivot": [0, 5.17991, -1.5507],
							"rotation": [45, 0, 0],
							"uv": {
								"north": {"uv": [15, 15], "uv_size": [1, 1]},
								"east": {"uv": [15, 15], "uv_size": [1, 1]},
								"south": {"uv": [15, 15], "uv_size": [1, 1]},
								"west": {"uv": [15, 15], "uv_size": [1, 1]},
								"up": {"uv": [16, 16], "uv_size": [-1, -1]},
								"down": {"uv": [16, 16], "uv_size": [-1, -1]}
							}
						},
						{
							"origin": [-0.6, 2.6, -0.33],
							"size": [1.2, 1.2, 0.3],
							"uv": {
								"north": {"uv": [14, 15], "uv_size": [1, 1]},
								"east": {"uv": [14, 15], "uv_size": [1, 1]},
								"south": {"uv": [14, 15], "uv_size": [1, 1]},
								"west": {"uv": [14, 15], "uv_size": [1, 1]},
								"up": {"uv": [15, 16], "uv_size": [-1, -1]},
								"down": {"uv": [15, 16], "uv_size": [-1, -1]}
							}
						},
						{
							"origin": [-0.6, 0.3, -1.73],
							"size": [1.2, 0.6, 0.3],
							"pivot": [0, 1.2, -0.18],
							"rotation": [-65, 0, 0],
							"uv": {
								"north": {"uv": [14, 15], "uv_size": [1, 1]},
								"east": {"uv": [14, 15], "uv_size": [1, 1]},
								"south": {"uv": [14, 15], "uv_size": [1, 1]},
								"west": {"uv": [14, 15], "uv_size": [1, 1]},
								"up": {"uv": [15, 16], "uv_size": [-1, -1]},
								"down": {"uv": [15, 16], "uv_size": [-1, -1]}
							}
						},
						{
							"origin": [-0.6, 0.3, -1.03],
							"size": [1.2, 0.5, 0.3],
							"pivot": [0, 1.2, -0.18],
							"rotation": [-65, 0, 0],
							"uv": {
								"north": {"uv": [14, 15], "uv_size": [1, 1]},
								"east": {"uv": [14, 15], "uv_size": [1, 1]},
								"south": {"uv": [14, 15], "uv_size": [1, 1]},
								"west": {"uv": [14, 15], "uv_size": [1, 1]},
								"up": {"uv": [15, 16], "uv_size": [-1, -1]},
								"down": {"uv": [15, 16], "uv_size": [-1, -1]}
							}
						},
						{
							"origin": [-0.6, 0.11506, -0.93636],
							"size": [1.2, 0.7, 0.3],
							"uv": {
								"north": {"uv": [14, 15], "uv_size": [1, 1]},
								"east": {"uv": [14, 15], "uv_size": [1, 1]},
								"south": {"uv": [14, 15], "uv_size": [1, 1]},
								"west": {"uv": [14, 15], "uv_size": [1, 1]},
								"up": {"uv": [15, 16], "uv_size": [-1, -1]},
								"down": {"uv": [15, 16], "uv_size": [-1, -1]}
							}
						},
						{
							"origin": [-0.6, 0.25657, 0.12302],
							"size": [1.2, 2.2, 0.3],
							"pivot": [0, 1.50657, -0.42698],
							"rotation": [25, 0, 0],
							"uv": {
								"north": {"uv": [14, 15], "uv_size": [1, 1]},
								"east": {"uv": [14, 15], "uv_size": [1, 1]},
								"south": {"uv": [14, 15], "uv_size": [1, 1]},
								"west": {"uv": [14, 15], "uv_size": [1, 1]},
								"up": {"uv": [15, 16], "uv_size": [-1, -1]},
								"down": {"uv": [15, 16], "uv_size": [-1, -1]}
							}
						},
						{
							"origin": [-0.6, 0.46043, 0.62152],
							"size": [1.2, 1.9, 0.3],
							"pivot": [0, 1.51043, -0.42848],
							"rotation": [-65, 0, 0],
							"uv": {
								"north": {"uv": [14, 15], "uv_size": [1, 1]},
								"east": {"uv": [14, 15], "uv_size": [1, 1]},
								"south": {"uv": [14, 15], "uv_size": [1, 1]},
								"west": {"uv": [14, 15], "uv_size": [1, 1]},
								"up": {"uv": [15, 16], "uv_size": [-1, -1]},
								"down": {"uv": [15, 16], "uv_size": [-1, -1]}
							}
						},
						{
							"origin": [-0.7, 3.42682, -1.6133],
							"size": [1.4, 1, 1.4],
							"pivot": [0, 4.02682, -0.9633],
							"rotation": [25, 0, 0],
							"uv": {
								"north": {"uv": [14, 15], "uv_size": [1, 1]},
								"east": {"uv": [14, 15], "uv_size": [1, 1]},
								"south": {"uv": [14, 15], "uv_size": [1, 1]},
								"west": {"uv": [14, 15], "uv_size": [1, 1]},
								"up": {"uv": [15, 16], "uv_size": [-1, -1]},
								"down": {"uv": [15, 16], "uv_size": [-1, -1]}
							}
						},
						{
							"origin": [-0.6, 3.70631, -7.15262],
							"size": [1.2, 1, 6.7],
							"uv": {
								"north": {"uv": [14, 15], "uv_size": [1, 1]},
								"east": {"uv": [14, 15], "uv_size": [1, 1]},
								"south": {"uv": [14, 15], "uv_size": [1, 1]},
								"west": {"uv": [14, 15], "uv_size": [1, 1]},
								"up": {"uv": [15, 16], "uv_size": [-1, -1]},
								"down": {"uv": [15, 16], "uv_size": [-1, -1]}
							}
						},
						{
							"origin": [-0.6, 4.59694, -1.49488],
							"size": [1.2, 1, 0.7],
							"uv": {
								"north": {"uv": [14, 15], "uv_size": [1, 1]},
								"east": {"uv": [14, 15], "uv_size": [1, 1]},
								"south": {"uv": [14, 15], "uv_size": [1, 1]},
								"west": {"uv": [14, 15], "uv_size": [1, 1]},
								"up": {"uv": [15, 16], "uv_size": [-1, -1]},
								"down": {"uv": [15, 16], "uv_size": [-1, -1]}
							}
						},
						{
							"origin": [-0.7, 5.09694, -1.39488],
							"size": [1.4, 0.2, 0.5],
							"uv": {
								"north": {"uv": [13, 15], "uv_size": [1, 1]},
								"east": {"uv": [13, 15], "uv_size": [1, 1]},
								"south": {"uv": [13, 15], "uv_size": [1, 1]},
								"west": {"uv": [13, 15], "uv_size": [1, 1]},
								"up": {"uv": [14, 16], "uv_size": [-1, -1]},
								"down": {"uv": [14, 16], "uv_size": [-1, -1]}
							}
						},
						{
							"origin": [-0.4, 4.63346, -7.3446],
							"size": [0.8, 0.8, 0],
							"uv": {
								"north": {"uv": [0, 0], "uv_size": [15, 15]}
							}
						}
					]
				}
			]
		}
	]
}