{
  "parent": "forge:item/default",
  "loader": "forge:separate-perspective",
  "base": {
    "credit": "Made with Blockbench",
    "parent": "builtin/entity",
    "texture_size": [
      128,
      128
    ],
    "gui_light": "front",
    "display": {
      "thirdperson_righthand": {
        "translation": [
          0,
          -3.25,
          -1.25
        ],
        "scale": [
          0.2,
          0.2,
          0.2
        ]
      },
      "thirdperson_lefthand": {
        "translation": [
          0,
          -3.25,
          -1.25
        ],
        "scale": [
          0.2,
          0.2,
          0.2
        ]
      },
      "firstperson_righthand": {
        "translation": [
          0,
          -3.25,
          -2.25
        ],
        "scale": [
          0.3,
          0.3,
          0.3
        ]
      },
      "firstperson_lefthand": {
        "translation": [
          0,
          -3.25,
          -2.25
        ],
        "scale": [
          0.3,
          0.3,
          0.3
        ]
      }
    }
  },
  "perspectives": {
    "gui": {
      "parent": "lobotomy:item/peak_weapon_2d"
    },
    "head": {
      "parent": "lobotomy:item/peak_weapon_2d"
    },
    "ground": {
      "parent": "lobotomy:item/peak_weapon_2d"
    },
    "fixed": {
      "parent": "lobotomy:item/peak_weapon_2d"
    }
  }
}